LICENSE
README.md
setup.py
open/text/embeddings/openai.py
open/text/embeddings/server/__main__.py
open/text/embeddings/server/app.py
open/text/embeddings/server/aws.py
open/text/embeddings/server/gzip.py
open_text_embeddings.egg-info/PKG-INFO
open_text_embeddings.egg-info/SOURCES.txt
open_text_embeddings.egg-info/dependency_links.txt
open_text_embeddings.egg-info/requires.txt
open_text_embeddings.egg-info/top_level.txt