Metadata-Version: 2.1
Name: open-text-embeddings
Version: 1.0.4
Summary: Open Source Text Embedding Models with OpenAI API-Compatible Endpoint
Home-page: https://github.com/limcheekin/open-text-embeddings
Author: Lim Chee Kin
Author-email: limcheekin@vobject.com
License: MIT
Classifier: Programming Language :: Python :: 3
Classifier: Programming Language :: Python :: 3.7
Classifier: Programming Language :: Python :: 3.8
Classifier: Programming Language :: Python :: 3.9
Classifier: Programming Language :: Python :: 3.10
Classifier: Programming Language :: Python :: 3.11
Requires-Python: >=3.7
Provides-Extra: server
License-File: LICENSE
